imjoy/VERSION
imjoy/__init__.py
imjoy/__main__.py
imjoy/apps.py
imjoy/asgi.py
imjoy/http.py
imjoy/minio.py
imjoy/options.py
imjoy/runner.py
imjoy/s3.py
imjoy/server.py
imjoy/utils.py
imjoy/apps/echo-service.html
imjoy/apps/imjoy-plugin-parser.html
imjoy/apps/playground.html
imjoy/core/__init__.py
imjoy/core/auth.py
imjoy/core/connection.py
imjoy/core/interface.py
imjoy/core/plugin.py
imjoy/static_files/lite.html
imjoy/templates/web-python-plugin.html
imjoy/templates/web-worker-plugin.html
imjoy/templates/window-plugin.html
tests/__init__.py
tests/conftest.py
tests/example_plugin.py
tests/test_asgi.py
tests/test_jupyter.py
tests/test_minio_client.py
tests/test_s3.py
tests/test_server.py
tests/test_server_apps.py
imjoy-0.11.20.dist-info/LICENSE
imjoy-0.11.20.dist-info/METADATA
imjoy-0.11.20.dist-info/WHEEL
imjoy-0.11.20.dist-info/entry_points.txt
imjoy-0.11.20.dist-info/top_level.txt
imjoy-0.11.20.dist-info/RECORD
