Metadata-Version: 2.1
Name: imjoy
Version: 0.11.20
Summary: ImJoy Plugin Engine for running Python plugins locally or remotely from ImJoy.io
Home-page: http://github.com/imjoy-team/ImJoy-Engine
Author: ImJoy Team
Author-email: imjoy.team@gmail.com
License: MIT
Platform: UNKNOWN
Requires-Python: >=3.7
License-File: LICENSE
Requires-Dist: aiobotocore (>=1.4.2)
Requires-Dist: aiofiles
Requires-Dist: fastapi (>=0.70.0)
Requires-Dist: imjoy-rpc (>=0.3.31)
Requires-Dist: msgpack (>=1.0.2)
Requires-Dist: numpy
Requires-Dist: pydantic[email] (>=1.8.2)
Requires-Dist: typing-extensions (>=3.7.4.3)
Requires-Dist: jinja2 (>=3)
Requires-Dist: python-dotenv (>=0.17.0)
Requires-Dist: python-engineio (==4.0.0)
Requires-Dist: python-jose (==3.3.0)
Requires-Dist: python-socketio[asyncio_client] (==5.0.4)
Requires-Dist: pyyaml
Requires-Dist: shortuuid (>=1.0.1)
Requires-Dist: uvicorn (>=0.13.4)
Provides-Extra: jupyter
Requires-Dist: jupyter (>=1.0.0) ; extra == 'jupyter'
Requires-Dist: ipykernel (>=5.1.4) ; extra == 'jupyter'
Requires-Dist: imjoy-jupyter-extension ; extra == 'jupyter'
Provides-Extra: server-apps
Requires-Dist: requests (>=2.26.0) ; extra == 'server-apps'
Requires-Dist: playwright (>=1.15.0) ; extra == 'server-apps'
